nat_gateway_setup/__init__.py
nat_gateway_setup/dnsmasq.py
nat_gateway_setup/firewall.py
nat_gateway_setup/nat_gateway_setup.py
nat_gateway_setup/network_interface.py
nat_gateway_setup/utils.py
nat_gateway_setup-0.11.0.dist-info/LICENSE.md
nat_gateway_setup-0.11.0.dist-info/METADATA
nat_gateway_setup-0.11.0.dist-info/WHEEL
nat_gateway_setup-0.11.0.dist-info/entry_points.txt
nat_gateway_setup-0.11.0.dist-info/RECORD
