Metadata-Version: 2.1
Name: nat-gateway-setup
Version: 0.11.0
Summary: A utility to configure a Linux machine as a gateway for a private network.
Author: Your Name
Author-email: youremail@example.com
Requires-Python: >=3.9,<4.0
Classifier: Programming Language :: Python :: 3
Classifier: Programming Language :: Python :: 3.9
Classifier: Programming Language :: Python :: 3.10
Classifier: Programming Language :: Python :: 3.11
Requires-Dist: argparse (>=1.4.0,<2.0.0)
Requires-Dist: click (>=8.0.1,<9.0.0)
Requires-Dist: distro (>=1.8.0,<2.0.0)
Requires-Dist: ipaddress (>=1.0.23,<2.0.0)
Requires-Dist: prompt-toolkit (>=3.0.18,<4.0.0)
Requires-Dist: pyroute2 (>=0.5.14,<0.6.0)
